{
    "AX": {
        "error": 0.06014627662787229, 
        "fit": "average_SEM", 
        "value": -0.01316226834896952
    }, 
    "CDD": {
        "error": 0.0001835070445138949, 
        "fit": "average_SEM", 
        "value": 0.00022672617560601794
    }, 
    "H1": {
        "error": 0.11832143556455002, 
        "fit": "average_SEM", 
        "value": 0.0435279038681377
    }, 
    "H2": {
        "error": 0.11893494965801307, 
        "fit": "average_SEM", 
        "value": 0.23641316038556398
    }, 
    "L1": {
        "error": 0.20124851170698976, 
        "fit": "average_SEM", 
        "value": -0.050118027460606146
    }, 
    "L2": {
        "error": 0.1236034913085747, 
        "fit": "average_SEM", 
        "value": -0.05195016037323512
    }
}