{
    "AX": {
        "error": 0.05310663967673211, 
        "fit": "average_SEM", 
        "value": -0.009414621587590469
    }, 
    "CDD": {
        "error": 0.00011878445258009924, 
        "fit": "average_SEM", 
        "value": 0.00011401087419168713
    }, 
    "H1": {
        "error": 0.11511589610738067, 
        "fit": "average_SEM", 
        "value": 0.04982827578787692
    }, 
    "H2": {
        "error": 0.11956390822677002, 
        "fit": "average_SEM", 
        "value": 0.2385133149723212
    }, 
    "L1": {
        "error": 0.16832934430948954, 
        "fit": "average_SEM", 
        "value": -0.059820734575623646
    }, 
    "L2": {
        "error": 0.12999216108776165, 
        "fit": "average_SEM", 
        "value": -0.043149356103579825
    }
}